{
  "project_info": {
    "project_number": "638824936740",
    "project_id": "myapp-30313",
    "storage_bucket": "myapp-30313.appspot.com"
  },
  "client": [
    {
      "client_info": {
        "mobilesdk_app_id": "1:638824936740:android:0bd007a3dbb4d10f31afb1",
        "android_client_info": {
          "package_name": "com.example.myapp"
        }
      },
      "oauth_client": [],
      "api_key": [
        {
          "current_key": "AIzaSyCy1bn5wPdlqKUWuS7lYPDkjO-Y5XP191g"
        }
      ],
      "services": {
        "appinvite_service": {
          "other_platform_oauth_client": []
        }
      }
    }
  ],
  "configuration_version": "1"
}